docs/__init__.py
docs/api_reference.md
docs/tutorials.md
docs/architecture_notes/design_principles.md
docs/architecture_notes/effaxnet_2d.md
docs/architecture_notes/effaxnet_3d.md
syntropy/__init__.py
syntropy/version.py
syntropy/core/__init__.py
syntropy/core/config.py
syntropy/core/registry.py
syntropy/core/utils.py
syntropy/examples/__init__.py
syntropy/tf/__init__.py
syntropy/tf/layers/__init__.py
syntropy/tf/layers/axial_attention.py
syntropy/tf/layers/channel_attention.py
syntropy/tf/layers/conv_blocks.py
syntropy/tf/models/__init__.py
syntropy/tf/models/builder.py
syntropy/tf/models/effaxnet_2d.py
syntropy/tf/models/effaxnet_3d.py
syntropy/tf/train/__init__.py
syntropy/tf/train/train_2d.py
syntropy/tf/train/train_3d.py
syntropy/torch/__init__.py
syntropy/torch/layers/__init__.py
syntropy/torch/layers/axial_attention.py
syntropy/torch/layers/channel_attention.py
syntropy/torch/layers/conv_blocks.py
syntropy/torch/models/__init__.py
syntropy/torch/models/builder.py
syntropy/torch/models/effaxnet_2d.py
syntropy/torch/models/effaxnet_3d.py
syntropy/torch/train/__init__.py
syntropy/torch/train/train_2d.py
syntropy/torch/train/train_3d.py
syntropy-0.1.0.dist-info/licenses/LICENSE
tests/__init__.py
tests/test_shapes.py
tests/test_tf_layers.py
tests/test_tf_models.py
tests/test_torch_layers.py
tests/test_torch_models.py
syntropy-0.1.0.dist-info/METADATA
syntropy-0.1.0.dist-info/WHEEL
syntropy-0.1.0.dist-info/top_level.txt
syntropy-0.1.0.dist-info/RECORD
