Metadata-Version: 2.4
Name: syntropy
Version: 0.1.0
Summary: Modular research library for Efficient Axial Networks and future models
Home-page: https://github.com/ishans2404/syntropy
Author: Ishan Singh
Author-email: Ishan Singh <ishans2404@gmail.com>
License: Apache-2.0
Project-URL: Homepage, https://github.com/ishans2404/syntropy
Project-URL: Documentation, https://github.com/ishans2404/syntropy#readme
Project-URL: Issues, https://github.com/ishans2404/syntropy/issues
Requires-Python: >=3.8
License-File: LICENSE
Requires-Dist: numpy>=1.21
Provides-Extra: tf
Requires-Dist: tensorflow>=2.13.0; extra == "tf"
Requires-Dist: keras>=2.13.0; extra == "tf"
Provides-Extra: torch
Requires-Dist: torch>=2.1.0; extra == "torch"
Requires-Dist: torchvision>=0.16.0; extra == "torch"
Dynamic: author
Dynamic: home-page
Dynamic: license-file
Dynamic: requires-python
